picodingchallenge_rb/__init__.py
picodingchallenge_rb/parser.py
picodingchallenge_rb-0.1.3.dist-info/METADATA
picodingchallenge_rb-0.1.3.dist-info/WHEEL
picodingchallenge_rb-0.1.3.dist-info/top_level.txt
picodingchallenge_rb-0.1.3.dist-info/RECORD
